[
  {
    "id": 1,
    "title": "About",
    "link": "#about",
    "subMenu": false
  },
  {
    "id": 2,
    "title": "Services",
    "link": "#services",
    "subMenu": false
  },
  {
    "id": 3,
    "title": "Markets",
    "link": "#markets",
    "subMenu": false
  },
  {
    "id": 4,
    "title": "Principles",
    "link": "#principles",
    "subMenu": false
  },
  {
    "id": 5,
    "title": "Candidates",
    "link": "#candidates",
    "subMenu": false
  },
  {
    "id": 6,
    "title": "Contact",
    "link": "#contact",
    "subMenu": false,
    "isButton": true
  }
]